lognimbus/__init__.py
lognimbus/config.py
lognimbus/context.py
lognimbus/logger.py
tests/__init__.py
tests/test_logger.py
lognimbus-0.1.2.dist-info/LICENSE
lognimbus-0.1.2.dist-info/METADATA
lognimbus-0.1.2.dist-info/WHEEL
lognimbus-0.1.2.dist-info/top_level.txt
lognimbus-0.1.2.dist-info/RECORD
