Metadata-Version: 2.1
Name: lognimbus
Version: 0.1.2
Summary: A YAML-based logging library with rich formatting for container and Kubernetes environments
Home-page: https://github.com/dmarshaltu/lognimbus
Author: Denis Tu
Author-email: dmarshaltu@gmail.com
Classifier: Programming Language :: Python :: 3
Classifier: License :: OSI Approved :: MIT License
Classifier: Operating System :: OS Independent
Requires-Python: >=3.6
License-File: LICENSE
Requires-Dist: PyYAML
Requires-Dist: rich
Requires-Dist: prometheus-client
